va/__init__.py
va/__main__.py
va/automation.py
va/configure_structlog.py
va/constants.py
va/execution_log_handler.py
va/llm.py
va/models.py
va/reconcile.py
va/review.py
va/skeleton.py
va/step.py
va/workflow.py
va/agent/__init__.py
va/agent/agent.py
va/agent/code_buffer.py
va/agent/prompt.py
va/agent/recovery.py
va/agent/tools.py
va/cli/__init__.py
va/cli/auth.py
va/clients/auth_connection_client.py
va/clients/execution_service_client.py
va/code/__init__.py
va/code/inspector.py
va/code/loader.py
va/code/mutator.py
va/code/trap.py
va/mcp_server/README.md
va/mcp_server/__init__.py
va/mcp_server/main.py
va/mcp_server/web_automation.py
va/playwright/__init__.py
va/playwright/checkpoint.py
va/playwright/dom_utils.py
va/playwright/extract_schemas.py
va/playwright/locator.py
va/playwright/login.py
va/playwright/page.py
va/playwright/playwright.py
va/playwright/step.py
va/playwright/tools.py
va/playwright/warc_utils.py
va/playwright/web_agent.py
va/playwright/orby/20250508.jinja2
va/playwright/orby/__init__.py
va/playwright/orby/actions.py
va/playwright/orby/demo.py
va/playwright/orby/subtask_agent.py
va/playwright/orby/template.py
va/playwright/orby/utils.py
va/store/__init__.py
va/store/in_memory.py
va/store/orby_store.py
va/store/store.py
va/store/execution/__init__.py
va/store/orby/__init__.py
va/store/orby/orby_client.py
va/store/orby/http/server.py
va/utils/__init__.py
va/utils/auth.py
buf/validate/expression_pb2.py
buf/validate/validate_pb2.py
buf/validate/priv/private_pb2.py
pb/v1alpha1/application_auth_connection_service_pb2.py
pb/v1alpha1/application_auth_connection_service_pb2_grpc.py
pb/v1alpha1/auth_connection_pb2.py
pb/v1alpha1/oauth2_token_pb2.py
va/protos/orby/va/public/execution_messages_pb2.py
va/protos/orby/va/public/execution_messages_pb2.pyi
va/protos/orby/va/public/execution_messages_pb2_grpc.py
va/protos/orby/va/public/execution_service_pb2.py
va/protos/orby/va/public/execution_service_pb2.pyi
va/protos/orby/va/public/execution_service_pb2_grpc.py
vibe_automation-0.11.0.dist-info/METADATA
vibe_automation-0.11.0.dist-info/WHEEL
vibe_automation-0.11.0.dist-info/entry_points.txt
vibe_automation-0.11.0.dist-info/RECORD
