Metadata-Version: 2.4
Name: vibe-automation
Version: 0.11.0
Summary: Vibe Automation
Keywords: automation,workflow
Classifier: Development Status :: 3 - Alpha
Classifier: Intended Audience :: Developers
Classifier: Programming Language :: Python :: 3
Classifier: Programming Language :: Python :: 3.10
Requires-Python: >=3.10
Requires-Dist: anthropic>=0.53.0
Requires-Dist: fastapi>=0.104.0
Requires-Dist: google-api-python-client>=2.172.0
Requires-Dist: grpcio>=1.74.0
Requires-Dist: instructor[anthropic]>=1.3.3
Requires-Dist: libcst>=1.0.0
Requires-Dist: mcp>=1.11.0
Requires-Dist: mypy-protobuf>=3.6.0
Requires-Dist: pandas>=2.0.0
Requires-Dist: playwright>=1.52.0
Requires-Dist: protobuf>=4.25.0
Requires-Dist: pydantic>=2.11.5
Requires-Dist: python-dotenv>=1.0.0
Requires-Dist: recordlinkage>=0.16.0
Requires-Dist: requests-oauthlib>=1.3.1
Requires-Dist: structlog>=24.1.0
Requires-Dist: typer>=0.16.0
Requires-Dist: uvicorn>=0.24.0
Requires-Dist: warcio>=1.7.5
